{"manufacturer": "Dovetail Workwear", "name": "Freshley Overall Cosy\u2122 Black Denim - Women's", "price": "219.99", "category_hierarchy": ["Women", "Women/Bottoms", "Women/Bottoms/Casual Pants"], "sku": "dov-dwf19o1w", "uid": "6075257782456", "review_score": "4.625", "review_total": "8", "url": "https://www.altitude-sports.com/products/dovetail-workwear-freshley-overall-cosy-black-denim-womens-llll-dov-dwf19o1w", "tech_specs": {"features": ["Straight silhouette", "2 pocket bib w/functional eyelet", "11 functional pockets total", "Hip clip pocket", "Flexible suspenders", "Double-front leg panels", "Reinforced rear cuff", "Fabric content: 72.5% Cotton/19% Polyester/5% Nylon/3.5% Spandex\n                            \n                    \n                \n                \n                \n\n\n\n\n    \n        ", "\n", "\n"]}, "img_urls": ["https://cdn.shopify.com/s/files/1/1230/9376/products/DOV-DWF19O1W_7EBlack_20Thermal_20Denim.jpg?v=1605166468"]}