{"manufacturer": "Houdini", "name": "Power Houdi - Women's", "price": "194.99", "category_hierarchy": ["Women", "Women/Tops", "Women/Tops/Hoodies", "Women/Tops/Running &amp; Training Shirts"], "sku": "hdi-125984", "uid": "4519998324839", "review_score": "4", "review_total": "4", "url": "https://www.altitude-sports.com/products/houdini-power-houdi-womens-llll-hdi-125984", "tech_specs": {"features": []}, "img_urls": ["https://cdn.shopify.com/s/files/1/1230/9376/products/HDI-125984_7ETrueblack_20-_20Trueblack_6f936711-deb7-4a0f-803a-e3b18a5157ca.jpg?v=1624170251"]}