{"manufacturer": "Marmot", "name": "All Around Tee Short Sleeve - Women's", "price": "34.99", "category_hierarchy": ["Women", "Women/Tops", "Women/Tops/Running &amp; Training Shirts", "Women/Tops/T-Shirts", "Women/Tops/Yoga Shirts"], "sku": "mar-56450", "uid": "10187091910", "review_score": "4.5667", "review_total": "17", "url": "https://www.altitude-sports.com/products/marmot-womens-all-around-tee-short-sleeve-llll-mar-56450", "tech_specs": {"features": ["Semi-Fitted", "Lightweight, Moisture Management Performance Knit Jersey", "Cottony Hand Polyester", "Ultraviolet Protection Factor (UPF) 30", "Quick-Drying and Wicking", "Flat-Locked Seams for Added Comfort", "Drop Tail Hem For Increased Coverage", "Set In Sleeves", "Scoop Neck", "Reflectivity"], "\u2022 Materials": " 93% Polyester, 7% Elastane Jersey 4.4 oz/yd", "\u2022 Weight": " 0lbs 5.99oz (169.8g)\n                            \n                    \n                \n                \n                \n\n\n\n\n    \n\n    \n\n    \n\n    \n\n    \n\n    \n\n\n"}, "img_urls": ["https://cdn.shopify.com/s/files/1/1230/9376/products/MAR-56450_7EClassic_20Blue.jpg?v=1624686863"]}