{"manufacturer": "MSR", "name": "DynaLock\u2122 Ascent Carbon 120cm Poles", "price": "189.99", "category_hierarchy": ["Gear", "Gear/Ski &amp; Backcountry", "Gear/Ski &amp; Backcountry/Ski Poles"], "sku": "msr-10236", "uid": "1460958560359", "review_score": "4.9231", "review_total": "8", "url": "https://www.altitude-sports.com/products/msr-dynalock-ascent-carbon-120cm-poles-llll-msr-10236", "tech_specs": {"features": ["Ultralight Strength: Kevlar\u00ae-reinforced carbon fiber construction.", "Packable: Quick-deploy design folds small to stash easily in smaller packs.", "Secure Adjustment: 20 cm of easy, rock-solid DynaLock\u2122 adjustability with tool-free tensioning; anodized aluminum lever provides lasting durability.", "Comfortable: EVA foam grip, plus lower grip for sidehilling or choking up on steep terrain.", "Versatile: Winter and summer baskets included for four-season functionality."]}, "img_urls": ["https://cdn.shopify.com/s/files/1/1230/9376/products/MSR-10236_7ECarbon_e0775840-c190-4539-a9ae-3919026f485d.jpg?v=1545290694"]}