{"manufacturer": "Nutcase", "name": "Baby Nutty Street Helmet", "price": "74.99", "category_hierarchy": ["Gear", "Gear/Helmets", "Gear/Helmets/Bike", "Gear/Helmets/Youth", "Youth"], "sku": "nut-bnut-1001", "uid": "10225117894", "review_score": "4.7949", "review_total": "26", "url": "https://www.altitude-sports.com/products/nutcase-baby-nutty-street-helmet-llll-nut-bnut-1001", "tech_specs": {"features": ["Finally, the baby helmet you\u2019ll both love: No pinch, no tears Fidlock\u00ae magnetic buckle", "Easy-on fit system grows with your toddler", "Ergo-design for optimal bike seat posture", "Lightweight inmold shell for growing bobble heads", "Expanded Polystyrene (EPS) protective foam for high-impact protection", "Front, top, and back venting ", "Integrated smile and compliment generator", "Engineered, tested, and CPSC certified for 1 year and older", "Lightweight for small heads, at 260 grams\n                            \n                    \n                \n                \n                \n\n\n\n\n    \n\n    \n\n    \n\n    \n\n    \n\n    \n\n    \n\n\n", "\n"]}, "img_urls": ["https://cdn.shopify.com/s/files/1/1230/9376/products/NUT-BNUT-1001_7EDinoite_20Gloss_dfcc3b92-9a85-455d-b9e0-69d9285ca17b.jpg?v=1624082668"]}