{"manufacturer": "Picture", "name": "Wailer Jacket - Men's", "price": "139.99", "category_hierarchy": ["Men", "Men/Jackets &amp; Vests", "Men/Jackets &amp; Vests/Camping &amp; Hiking Coats &amp; Vests", "Men/Jackets &amp; Vests/Softshells &amp; Windbreakers", "Men/Jackets &amp; Vests/Urban Coats &amp; Vests"], "sku": "pce-mvt326", "uid": "6645419081912", "review_score": "0", "review_total": "0", "url": "https://www.altitude-sports.com/products/picture-wailer-jacket-mens-llll-pce-mvt326", "tech_specs": {"features": ["30D ultralight", "Windbreaker", "Pullover jacket", "Teflon Ecoelite\u2122 PFC free DWR treatment", "Packable with self stowing pocket", "Elasticated ergonomic hood", "Zippered pouch pocket", "Elasticated wrists", "Ykk half zipper", "Picture expedition puller", "Reflective details", "Expedition print", "Global recycled standard"]}, "img_urls": ["https://cdn.shopify.com/s/files/1/1230/9376/products/PCE-MVT326_7EIceberg.jpg?v=1619682199"]}