{"manufacturer": "SOIA &amp; KYO", "name": "Ciel Tuque, Turkey Fur Pompom - Women's", "price": "75", "category_hierarchy": ["Women", "Women/Headwear &amp; Neckwear", "Women/Headwear &amp; Neckwear/Hats &amp; Toques"], "sku": "syo-ciel", "uid": "4096652410983", "review_score": "4.5833", "review_total": "14", "url": "https://www.altitude-sports.com/products/soia-kyo-ciel-tuque-turkey-fur-pompom-womens-llll-syo-ciel", "tech_specs": {"features": []}, "img_urls": ["https://cdn.shopify.com/s/files/1/1230/9376/products/SYO-CIEL_7EBlack.jpg?v=1610175587"]}