{"manufacturer": "Salomon", "name": "Flexfit\u00ae Logo Cap - Men's", "price": "39.99", "category_hierarchy": ["Men", "Men/Headwear &amp; Neckwear", "Men/Headwear &amp; Neckwear/Caps &amp; Sun Hats"], "sku": "sal-lc1535500", "uid": "6589331734712", "review_score": "5", "review_total": "1", "url": "https://www.altitude-sports.com/products/salomon-flexfit-logo-cap-mens-llll-sal-lc1535500", "tech_specs": {"features": ["Optimized fit: Flexfit\u00ae Tech means that spandex is woven into the sweatband and crown for added elasticity", "Perfect temperature: The wool blend keeps the cold at bay but is also naturally very breathable", "Versatile wear: Easy to wear every day to protect you from the sun, drizzle or simply complete your look"]}, "img_urls": ["https://cdn.shopify.com/s/files/1/1230/9376/products/SAL-LC1535500_7EBronze_20Brown.jpg?v=1623826974"]}