{"manufacturer": "Thule", "name": "Spring Aluminum", "price": "449.95", "category_hierarchy": ["Gear", "Gear/Child Carriers &amp; Strollers", "Gear/Child Carriers &amp; Strollers/City Strollers"], "sku": "thu-11300102", "uid": "4531075383399", "review_score": "4.8", "review_total": "4", "url": "https://www.altitude-sports.com/products/thule-spring-aluminum-llll-thu-11300102", "tech_specs": {"features": []}, "img_urls": ["https://cdn.shopify.com/s/files/1/1230/9376/products/THU-11300102_7EAluminum_20-_20Majolica_20Blue.jpg?v=1625041444"]}