{"manufacturer": "Victorinox", "name": "Lexicon Hardside Global Carry-On", "price": "574.99", "category_hierarchy": ["Gear", "Gear/Packs &amp; Bags", "Gear/Packs &amp; Bags/Luggage &amp; Carry-On"], "sku": "vic-602103", "uid": "4528206512231", "review_score": "5", "review_total": "2", "url": "https://www.altitude-sports.com/products/victorinox-lexicon-hardside-global-carry-on-llll-vic-602103", "tech_specs": {"features": []}, "img_urls": ["https://cdn.shopify.com/s/files/1/1230/9376/products/VIC-602103_7ETitanium.jpg?v=1584773837"]}