{"manufacturer": "Adidas", "name": "Ultraboost 21 Performance Shoes - Women's", "price": "249.99", "category_hierarchy": ["Footwear", "Footwear/Women", "Footwear/Women/Running Shoes", "Women"], "sku": "adi-fy0401", "uid": "6143079121080", "review_score": "5", "review_total": "1", "url": "https://www.altitude-sports.com/products/adidas-ultraboost-21-performance-shoes-womens-llll-adi-fy0401", "tech_specs": {"features": ["Lace closure", "Adidas Primeknit+upper", "Textile lining", "Supportive heel counter", "Boost midsole"], "Specifications": {"Support": "Neutral", "Drop": "10 mm", "Terrain": "Road", "Heel Height": "30.50 mm", "Forefoot Height": "20.50 mm", "Weight": "340 g", "Width": "Normal"}}, "img_urls": ["https://cdn.shopify.com/s/files/1/1230/9376/products/ADI-FY0401_7ECore_20Black_20-_20Core_20Black_20-_20Grey_20Four.jpg?v=1610868074"]}