{"manufacturer": "Brixton", "name": "Joanna Rancher Hat - Women's", "price": "99.99", "category_hierarchy": ["Women", "Women/Headwear &amp; Neckwear", "Women/Headwear &amp; Neckwear/Hats &amp; Toques"], "sku": "brx-10842", "uid": "6615986929848", "review_score": "0", "review_total": "0", "url": "https://www.altitude-sports.com/products/brixton-joanna-rancher-hat-womens-llll-brx-10842", "tech_specs": {"features": ["Felt", "Grosgrain band and brim taping", "Metal headwear plaque", "Adjustable Velcro strap under sweatband.\n                            \n                    \n                \n                \n                \n\n\n\n\n    \n\n    \n\n    \n\n    \n\n\n", "\n"]}, "img_urls": ["https://cdn.shopify.com/s/files/1/1230/9376/products/BRX-10842_7EToffee_e73cf888-1871-4935-b659-fc363be473c4.jpg?v=1618559699"]}