{"manufacturer": "Burton", "name": "Multipath Active Short Sleeve T-Shirt - Men's", "price": "49.99", "category_hierarchy": ["Men", "Men/Tops", "Men/Tops/Running &amp; Training Shirts", "Men/Tops/T-Shirts"], "sku": "btn-21759101", "uid": "6575165374648", "review_score": "0", "review_total": "0", "url": "https://www.altitude-sports.com/products/burton-multipath-active-short-sleeve-t-shirt-mens-llll-btn-21759101", "tech_specs": {"features": ["Regular fit is just right: Not too tight or too baggy", "Polyester and cotton-bend jersey", "Dryride Ultrawick is highly breathable and ultra-fast wicking", "Pre-shrunk", "Soft-touch screen-printed logo", "Lifetime Warranty\n                            \n                    \n                \n                \n                \n\n\n\n\n    \n\n    \n\n    \n\n    \n        ", "\n", "\n"]}, "img_urls": ["https://cdn.shopify.com/s/files/1/1230/9376/products/BTN-21759101_7ESummer_20Green_23cbb584-77c0-470d-89c4-d4b6b2684e56.jpg?v=1619851813"]}