{"manufacturer": "Bellelli", "name": "Freccia Standard Front Bike Seat", "price": "129.99", "category_hierarchy": ["Gear", "Gear/Bike Accessories", "Gear/Bike Accessories/Seats &amp; Saddles", "Gear/Child Carriers &amp; Strollers", "Gear/Child Carriers &amp; Strollers/Child Carriers"], "sku": "bll-01frcb0002", "uid": "6557169778872", "review_score": "5", "review_total": "1", "url": "https://www.altitude-sports.com/products/bellelli-freccia-standard-front-bike-seat-llll-bll-01frcb0002", "tech_specs": {"features": ["Nontoxic certified plastic frame, lightweight, solid, and washable", "Wide ventilation slots on back and shoulders", "Soft, removable, and washable seat pad", "Three-point length-adjustable safety belts", "Broad footrest height-setting range: 11 cm \u2013 4.4\u201d", "Length-adjustable foot straps (4 positions)", "Wider and safer legs/feet side protection to avoid any contact with wheel spokes", "Childproof, parent-friendly safety buckle with two depth settings in the centre of the seat. Only one hand is needed to fasten and release it", "Wide and comfortable seats with high sideboards to increase child support and containment", "One click, easy on/Easy-Off protection handle", "Bellelli Freccia can be used with the B-FIX mounting system.\n                            \n                    \n                \n                \n                \n\n\n\n\n    \n\n    \n\n\n", "\n"]}, "img_urls": ["https://cdn.shopify.com/s/files/1/1230/9376/products/BLL-01FRCB0002_7EGrey.jpg?v=1615448237"]}