{"manufacturer": "Burton", "name": "Carlow Short Sleeve T-Shirt - Women's", "price": "39.99", "category_hierarchy": ["Women", "Women/Tops", "Women/Tops/T-Shirts"], "sku": "btn-22612100", "uid": "6685260939448", "review_score": "0", "review_total": "0", "url": "https://www.altitude-sports.com/products/burton-carlow-short-sleeve-t-shirt-womens-llll-btn-22612100", "tech_specs": {"features": ["Regular fit is just right: Not too tight or too baggy", "Made with organic Peruvian cotton", "Ribbed collar and cuffs", "Pre-shrunk", "Soft-touch screen-printed logo\n                            \n                    \n                \n                \n                \n\n\n\n\n    \n        ", "\n", "\n"]}, "img_urls": ["https://cdn.shopify.com/s/files/1/1230/9376/products/BTN-22612100_7EGray_20Heather.jpg?v=1621753859"]}