{"manufacturer": "BLACKYAK", "name": "Brangus Pants - Women's", "price": "699.99", "category_hierarchy": ["Women", "Women/Bottoms", "Women/Bottoms/Ski &amp; Snowboard Pants", "Women/Bottoms/Waterproof Pants"], "sku": "bak-1811072", "uid": "4721993187431", "review_score": "5", "review_total": "1", "url": "https://www.altitude-sports.com/products/blackyak-brangus-pants-womens-llll-bak-1811072", "tech_specs": {"features": ["2 hand warmer pockets with zippers", "2 cargo pockets with zippers", "1 bib pocket for secure storage", "Ergonomic stretch panels", "Long side 2-way ventilation zippers", "Large Kevlar\u00ae protection area", "High waistband with integrated belt system (G-Hook)", "Snow gaiter with shoe hook", "Innovative suspender solution\n                            \n                    \n                \n                \n                \n\n\n\n\n    \n\n\n", "\n"]}, "img_urls": ["https://cdn.shopify.com/s/files/1/1230/9376/products/BAK-1811072_7EBlack_20Beauty.jpg?v=1601445795"]}