{"manufacturer": "Dickies", "name": "Short Sleeve Work Shirt - Men's", "price": "39.99", "category_hierarchy": ["Men", "Men/Tops", "Men/Tops/Dress Shirts &amp; Button-Down"], "sku": "dic-1574", "uid": "4721495539815", "review_score": "4.2", "review_total": "4", "url": "https://www.altitude-sports.com/products/dickies-short-sleeve-work-shirt-mens-llll-dic-1574", "tech_specs": {"features": ["\n", "Generous fit in shoulders and chest\n", "5.25 oz. Twill, 65% Polyester/35% Cotton\n", "Our most popular, most versatile short sleeve work shirt\n", "Resists wrinkles\n", "Moisture-wicking for comfortable wear\n", "Square tail design stays tucked in\n", "Colors match our Original 874\u00ae\n", "Wrinkle resistant\n", "Non-break melamine buttons\n", "Colors match our Original 874\u00ae Work Pant\n", "Square tail design stays tucked in\n", "Imported\n                            \n                    \n                \n                \n                \n\n\n\n\n    \n\n    \n\n    \n\n    \n\n    \n\n    \n\n    \n\n    \n\n    \n\n    \n\n\n", "\n"]}, "img_urls": ["https://cdn.shopify.com/s/files/1/1230/9376/products/DIC-1574_7ECharcoal_db82407d-37b6-46ed-b08e-9d0712c485c7.jpg?v=1601706621"]}