{"manufacturer": "Giro", "name": "Jag'ette Gloves - Women's", "price": "34.99", "category_hierarchy": ["Women", "Women/Gloves &amp; Mitts", "Women/Gloves &amp; Mitts/Gloves"], "sku": "gio-gh-7076428", "uid": "2124622954599", "review_score": "4.3333", "review_total": "2", "url": "https://www.altitude-sports.com/products/giro-jagette-gloves-womens-llll-gio-gh-7076428", "tech_specs": {"features": ["Upper: Moisture-wicking four-way-stretch Lycra", "Highly absorbent microfiber wiping surface", "Low-profile Velcro\u00ae closure", "Palm: Super Fit\u2122 engineered three-panel design", "AX Suede\u2122 microfiber palm", "Sonic-welded pull tab", "Padding: Optimized EVA padding\n                            \n                    \n                \n                \n                \n\n\n\n\n    \n\n    \n\n    \n\n    \n\n    \n\n    \n\n\n", "\n"]}, "img_urls": ["https://cdn.shopify.com/s/files/1/1230/9376/products/GIO-GH-7076428_7EMagenta.jpg?v=1623140181"]}