{"manufacturer": "GSI Outdoors", "name": "Gourmet 10 Inch Frypan", "price": "50.99", "category_hierarchy": ["Gear", "Gear/Camp Kitchen", "Gear/Camp Kitchen/Pots &amp; Pans"], "sku": "gsi-68110", "uid": "1421129613415", "review_score": "3", "review_total": "1", "url": "https://www.altitude-sports.com/products/gsi-outdoors-gourmet-10-frypan-llll-gsi-68110", "tech_specs": {"features": ["Gourmet, stainless steel exterior surrounds heavy-gauge, clad aluminum core for quick heating combined with the unrivaled durability which only stainless steel can provide.", "Durable, laser-etched nonstick surface offers excellent food release and easy cleanup.", "Exclusive SureLock\u2122 folding handle."]}, "img_urls": ["https://cdn.shopify.com/s/files/1/1230/9376/products/GSI-68110_7EBrushed_20Stainless_20-_20Silver.jpg?v=1535173244"]}