{"manufacturer": "Icebreaker", "name": "Flaxen LS Hooded Pullover Sweater - Women's", "price": "209.99", "category_hierarchy": ["Women", "Women/Tops", "Women/Tops/Merino Shirts", "Women/Tops/Sweaters, Sweatshirts &amp; Long Sleeve"], "sku": "ice-ib105369", "uid": "6587207909560", "review_score": "5", "review_total": "2", "url": "https://www.altitude-sports.com/products/icebreaker-flaxen-ls-hooded-pullover-sweater-womens-llll-ice-ib105369", "tech_specs": {"features": []}, "img_urls": ["https://cdn.shopify.com/s/files/1/1230/9376/products/ICE-IB105369_7EMilkwood_20Heather.jpg?v=1616654741"]}