{"manufacturer": "Julbo", "name": "Romy Sunglasses - Shiny White-Mat Pastel Blue - Spectron 3CF Brown Lens", "price": "53.99", "category_hierarchy": ["Gear", "Gear/Sunglasses", "Gear/Sunglasses/Casual"], "sku": "jul-508-1111", "uid": "292636131349", "review_score": "0", "review_total": "0", "url": "https://www.altitude-sports.com/products/julbo-romy-shiny-white-mat-pastel-blue-spectron-3cf-brown-lens-llll-jul-508-1111", "tech_specs": {"features": ["Wrap-around style : Wrap around shape for a good vision spectrum and protection.", "Curved temples : For good hold on the face and head.", "Grip Tech : Flexible inserts adhere to the temples for maximum hold and comfort.", "Cord attachement holes : Allow attachment of a cord."]}, "img_urls": ["https://cdn.shopify.com/s/files/1/1230/9376/products/JUL-508-1111_7EMat_20Pink_20Spectron.jpg?v=1595485279"]}