{"manufacturer": "Nathan", "name": "Hyperbrite Strobe Led Light", "price": "19.99", "category_hierarchy": ["Gear", "Gear/Lighting", "Gear/Lighting/Flashlights"], "sku": "nat-ns5112", "uid": "4024291328103", "review_score": "3.5", "review_total": "6", "url": "https://www.altitude-sports.com/products/nathan-hyperbrite-strobe-led-light-llll-nat-ns5112", "tech_specs": {"features": []}, "img_urls": ["https://cdn.shopify.com/s/files/1/1230/9376/products/NAT-NS5112_7EChili_20Pepper_20-_20White.jpg?v=1609830906"]}