{"manufacturer": "Peak Performance", "name": "Rider Zip Hood - Men's", "price": "159.99", "category_hierarchy": ["Men", "Men/Tops", "Men/Tops/Hoodies", "Men/Tops/Running &amp; Training Shirts"], "sku": "pkp-g75441010", "uid": "6571763695800", "review_score": "5", "review_total": "1", "url": "https://www.altitude-sports.com/products/peak-performance-rider-zip-hood-mens-llll-pkp-g75441010", "tech_specs": {"features": ["Full centre front zip", "Zipped pockets", "Cozy high fitting hood", "Regular fit"]}, "img_urls": ["https://cdn.shopify.com/s/files/1/1230/9376/products/PKP-G75441010_7EBlue_20Shadow.jpg?v=1616046949"]}