{"manufacturer": "Patagonia", "name": "Baggies Jacket - Men's", "price": "149", "category_hierarchy": ["Men", "Men/Jackets &amp; Vests", "Men/Jackets &amp; Vests/Camping &amp; Hiking Coats &amp; Vests"], "sku": "pat-28151", "uid": "4512925614183", "review_score": "4.875", "review_total": "8", "url": "https://www.altitude-sports.com/products/patagonia-baggies-jacket-mens-llll-pat-28151", "tech_specs": {"features": []}, "img_urls": ["https://cdn.shopify.com/s/files/1/1230/9376/products/PAT-28151_7EStone_20Blue.jpg?v=1614068456"]}