{"manufacturer": "Patagonia", "name": "\u00a0Ultralight Black Hole\u00ae Sling 8L", "price": "75", "category_hierarchy": ["Gear", "Gear/Packs &amp; Bags", "Gear/Packs &amp; Bags/Waistpacks"], "sku": "pat-49020", "uid": "4518647857255", "review_score": "4.6364", "review_total": "6", "url": "https://www.altitude-sports.com/products/patagonia-ultralight-black-hole-sling-8l-llll-pat-49020", "tech_specs": {"features": []}, "img_urls": ["https://cdn.shopify.com/s/files/1/1230/9376/products/PAT-49020_7EPatchwork_20-_20Curacao_20Blue.jpg?v=1625379654"]}