{"manufacturer": "Reebok", "name": "Classic Leather Shoes - Big Boys", "price": "74.99", "category_hierarchy": ["Footwear", "Footwear/Youth", "Footwear/Youth/Boys' Shoes, Boots, Sandals &amp; Slippers", "Youth"], "sku": "rbk-ar1146", "uid": "6626406170808", "review_score": "0", "review_total": "0", "url": "https://www.altitude-sports.com/products/reebok-classic-leather-shoes-big-boys-llll-rbk-ar1146", "tech_specs": {"features": ["Low-cut design for a sleek and sophisticated silhouette", "Die-cut EVA midsole designed for cushioning", "Rubber outsole designed for durable responsiveness\n                            \n                    \n                \n                \n                \n\n\n\n\n    \n\n    \n\n    \n\n    \n\n    \n\n    \n\n    \n\n    \n\n    \n\n    \n\n    \n\n    \n\n\n", "\n"]}, "img_urls": ["https://cdn.shopify.com/s/files/1/1230/9376/products/RBK-AR1146_7EWhite_20-_20Gum.jpg?v=1618557218"]}