{"manufacturer": "Rossignol", "name": "Heritage Grey Sneakers - Women's", "price": "149.99", "category_hierarchy": ["Footwear", "Footwear/Women", "Footwear/Women/Casual Shoes &amp; Urban Boots", "Women"], "sku": "rss-rniwh20", "uid": "4726044590183", "review_score": "4", "review_total": "1", "url": "https://www.altitude-sports.com/products/rossignol-heritage-grey-sneakers-womens-llll-rss-rniwh20", "tech_specs": {"features": ["Lacings Oval lace 6mm - POLYESTER", "Materials Texitle", "Thermal insulation NO", "Insole Textile / EVA Padding", "Materials EVA / Rubber", "Properties EVA / Rubber", "Materials Suede leather / Textile", "Waterproofness NO\n                            \n                    \n                \n                \n                \n\n\n\n\n    \n\n    \n\n    \n\n    \n\n    \n\n    \n\n    \n\n    \n\n\n", "\n"]}, "img_urls": ["https://cdn.shopify.com/s/files/1/1230/9376/products/RSS-RNIWH20_7EGrey.jpg?v=1618988271"]}