{"manufacturer": "Salomon", "name": "Sight Crew Neck Pullover - Women's", "price": "69.99", "category_hierarchy": ["Women", "Women/Tops", "Women/Tops/Sweaters, Sweatshirts &amp; Long Sleeve"], "sku": "sal-lc1420400", "uid": "6123192778936", "review_score": "4.8571", "review_total": "5", "url": "https://www.altitude-sports.com/products/salomon-sight-crew-neck-pullover-womens-llll-sal-lc1420400", "tech_specs": {"features": ["Regular Fit: On tops and bottoms, Regular fit is a wider fir than active fit, but slimmer than relaxed fit", "AdvancedSkin Warm: AdvancedSkin technical fabrics improve body comfort by keeping you dry, warm and protected when you need it and where you need it", "2 hand pockets: Roomy pockets to keep your hands warm"]}, "img_urls": ["https://cdn.shopify.com/s/files/1/1230/9376/products/SAL-LC1420400_7EAlloy_20-_20Lunar_20Rock_20-_20Heather.jpg?v=1610183220"]}