{"manufacturer": "Smartwool", "name": "Athletic Ultra Light Crew Socks - Kids", "price": "14.99", "category_hierarchy": ["Youth", "Youth/Boy", "Youth/Boy/Socks", "Youth/Girl", "Youth/Girl/Socks"], "sku": "smt-sw001489", "uid": "6161978425528", "review_score": "4.6667", "review_total": "9", "url": "https://www.altitude-sports.com/products/smartwool-athletic-ultra-light-crew-socks-kids-llll-smt-sw001489", "tech_specs": {"features": ["Designed to fit perfectly in kids\u2019 shoes without adding unnecessary bulk", "Sizing clearly indicated on the sock", "Flat knit toe seam for additional comfort", "Elasticized arch brace for secure fit", "Product End Use: Hiking", "Silhouette 1: Zero Cushion", "Silhouette 2: Crew.\n                            \n                    \n                \n                \n                \n\n\n\n\n    \n\n    \n\n    \n\n    \n\n    \n\n    \n\n    \n\n    \n\n    \n\n    \n\n    \n\n    \n\n\n", "\n"]}, "img_urls": ["https://cdn.shopify.com/s/files/1/1230/9376/products/SMT-SW001489_7EDeep_20Navy.jpg?v=1617346187"]}