{"manufacturer": "Alo Yoga", "name": "Cover Tank - Women's", "price": "77.99", "category_hierarchy": ["Women", "Women/Tops", "Women/Tops/Tank Tops &amp; Sleeveless", "Women/Tops/Yoga Shirts"], "sku": "alo-w2564r", "uid": "2050667774055", "review_score": "4.8889", "review_total": "5", "url": "https://www.altitude-sports.com/products/alo-yoga-womens-cover-tank-llll-alo-w2564r", "tech_specs": {"features": ["Draping jersey.", "Fitted cropped silhouette", "On-trend raw edge hem fabric is softer than soft.", "Fit: Fitted cropped tank silhouette", "Ultra feminine front wrap detail", "Wear-tested by our in-house team for the perfect fit", "Fabrication: Moisture-wicking antimicrobial technology. 4-way-stretch fabric for a move-with-you feel.", "Fabric: Rayon Spandex Jersey 94% Rayon 6% Spandex\n                            \n                    \n                \n                \n                \n\n\n\n\n    \n\n    \n\n    \n\n    \n\n\n", "\n"]}, "img_urls": ["https://cdn.shopify.com/s/files/1/1230/9376/products/ALO-W2564R_7EAnthracite_20Heather.jpg?v=1623910748"]}