{"manufacturer": "Adventure Medical Kits", "name": "Natrapel\u00ae Lemon Eucalyptus Spray 37 ml", "price": "6.99", "category_hierarchy": ["Gear", "Gear/Health &amp; Safety", "Gear/Health &amp; Safety/First Aid Kits &amp; Supplies"], "sku": "amk-0007-6700", "uid": "10046216070", "review_score": "4", "review_total": "3", "url": "https://www.altitude-sports.com/products/adventure-medical-kits-natrapel-lemon-eucalyptus-spray-37-ml-llll-amk-0007-6700", "tech_specs": {"features": ["Plant Based Active Ingredient (derived from lemon eucalyptus tree)", "Up to 8 hours of protection", "DEET-Free formula won't melt jackets, fishing line, and other plastics", "Easy Pump Spray Application", "Airplane Travel Friendly Sizes", "Cool Refreshing Lemon Eucalyptus Scent", "37ml Spray\n                            \n                    \n                \n                \n                \n\n\n\n\n    \n\n\n", "\n"]}, "img_urls": ["https://cdn.shopify.com/s/files/1/1230/9376/products/AMK-0007-6700_7ENo_20Color_ef0e681e-c1fb-4ade-abe2-1a23acd5a9d0.jpg?v=1551935528"]}