{"manufacturer": "ASICS", "name": "Rinkan Boot - Unisex", "price": "199.99", "category_hierarchy": ["Footwear", "Footwear/Men", "Footwear/Men/Casual Shoes &amp; Urban Boots", "Footwear/Men/Casual Shoes &amp; Urban Boots/Casual Boots", "Footwear/Men/Leather Boots &amp; Shoes", "Footwear/Women", "Footwear/Women/Casual Shoes &amp; Urban Boots", "Footwear/Women/Leather Boots &amp; Shoes", "Men", "Women"], "sku": "acs-1183a854", "uid": "6651402748088", "review_score": "0", "review_total": "0", "url": "https://www.altitude-sports.com/products/asics-rinkan-boot-unisex-llll-acs-1183a854", "tech_specs": {"features": ["Oiled-leather upper", "High-top silhouette", "Rubber sole", "Ortholite\u00ae insole", "Suede stripes", "Signature branding\n                            \n                    \n                \n                \n                \n\n\n\n\n    \n\n    \n\n    \n\n    \n\n    \n\n    \n\n    \n\n    \n\n    \n\n    \n\n\n", "\n"]}, "img_urls": ["https://cdn.shopify.com/s/files/1/1230/9376/products/ACS-1183A854_7ECoffee_20-_20Graphite_20Grey.jpg?v=1619939679"]}