{"manufacturer": "Carhartt Work In Progress", "name": "Ruck Single Knee Short - Men's", "price": "172.99", "category_hierarchy": ["Men", "Men/Bottoms", "Men/Bottoms/Casual Shorts"], "sku": "crt-i024892", "uid": "4518660964455", "review_score": "4.9", "review_total": "6", "url": "https://www.altitude-sports.com/products/carhartt-work-in-progress-ruck-single-knee-short-mens-llll-crt-i024892", "tech_specs": {"features": ["Regular fit, regular waist", "Triple stitched", "Bartack stitching at vital stress points", "Tool pockets and hammer loop", "Square label", "Zip fly"]}, "img_urls": ["https://cdn.shopify.com/s/files/1/1230/9376/products/CRT-I024892_7EDollar_20Green_20-_20Stone_20Washed_f0326464-bcbb-4366-ae33-28296a465729.jpg?v=1619591655"]}