{"manufacturer": "Darn Tough", "name": "Coolmax\u00ae Run No Show Tab Ultra-Lightweight Running Sock - Women's", "price": "20.99", "category_hierarchy": ["Women", "Women/Socks", "Women/Socks/Running &amp; Training Socks"], "sku": "dat-1051", "uid": "6540262801592", "review_score": "5", "review_total": "2", "url": "https://www.altitude-sports.com/products/darn-tough-coolmax-run-no-show-tab-ultra-lightweight-running-sock-womens-llll-dat-1051", "tech_specs": {"features": ["Performance Fit: No slipping, no bunching, and no blisters", "Fine Gauge Knitting: Unprecedented durability and our unique \u201cput it on, forget it\u2019s on\u201d feel", "Fast Action Wicking: Pulls moisture away from skin. Fast drying", "All Weather Performance: Cool in the summer, warm in the winter", "Naturally Antimicrobial: Repels bacteria and odor", "Guaranteed For Life: No strings. No conditions. For life", "COOLMAX\u00ae is engineered to move moisture away from your skin and dry fast in warm conditions", "True Seamless\u2122: Undetectable seam fusion for an ultra smooth, invisible feel."]}, "img_urls": ["https://cdn.shopify.com/s/files/1/1230/9376/products/DAT-1051_7EWhite.jpg?v=1614495735"]}