{"manufacturer": "Garneau", "name": "Course Superleggera Glasses", "price": "54.99", "category_hierarchy": ["Gear", "Gear/Sunglasses", "Gear/Sunglasses/Cycling", "Gear/Sunglasses/Running"], "sku": "lgn-1490204", "uid": "10482695317", "review_score": "5", "review_total": "3", "url": "https://www.altitude-sports.com/products/garneau-course-superleggera-glasses-llll-lgn-1490204", "tech_specs": {"features": ["Grilamid TR-90 nylon vented frame", "Polymer inserts in the bridge and stems: Better support of glasses during activities", "Vented 7 base curve PC lens", "Fit: Medium-Large", "Weight: 25 g", "Microfiber Bag Included", "Feather Weight\n                            \n                    \n                \n                \n                \n\n\n\n\n    \n\n    \n\n\n", "\n"]}, "img_urls": ["https://cdn.shopify.com/s/files/1/1230/9376/products/LGN-1490204_7EGreen.jpg?v=1552979877"]}