{"manufacturer": "Norse Projects", "name": "Osvald Button Down Cotton Linen Shirt - Men's", "price": "220.99", "category_hierarchy": ["Men", "Men/Tops", "Men/Tops/Dress Shirts &amp; Button-Down"], "sku": "nps-n40-0551", "uid": "6729394946232", "review_score": "0", "review_total": "0", "url": "https://www.altitude-sports.com/products/norse-projects-osvald-button-down-cotton-linen-shirt-mens-llll-nps-n40-0551", "tech_specs": {"features": ["Regular Fit", "Chest Pockets", "Mother-of-Pearl Buttons", "Indian Fabric", "50% Cotton, 50% Linen", "Made in Portugal\n                            \n                    \n                \n                \n                \n\n\n\n\n    \n\n    \n\n    \n\n    \n\n    \n\n    \n\n    \n\n    \n\n    \n\n    \n\n\n", "\n"]}, "img_urls": ["https://cdn.shopify.com/s/files/1/1230/9376/products/NPS-N40-0551_7EUltra_20Marine.jpg?v=1624002729"]}