{"manufacturer": "Nathan", "name": "SpeedDraw Insulated Flask - 18oz", "price": "19.99", "category_hierarchy": ["Gear", "Gear/Camp Kitchen", "Gear/Camp Kitchen/Bottles &amp; Thermoses"], "sku": "nat-ns4005", "uid": "4669368598631", "review_score": "5", "review_total": "3", "url": "https://www.altitude-sports.com/products/nathan-speeddraw-insulated-flask-18oz-llll-nat-ns4005", "tech_specs": {"features": []}, "img_urls": ["https://cdn.shopify.com/s/files/1/1230/9376/products/NAT-NS4005_7ESilver.jpg?v=1596694708"]}