{"manufacturer": "Osprey", "name": "Document Zip", "price": "59.99", "category_hierarchy": ["Men", "Men/Accessories", "Men/Accessories/Wallets", "Women", "Women/Accessories", "Women/Accessories/Wallets"], "sku": "osp-doczip", "uid": "11631176981", "review_score": "4.35", "review_total": "11", "url": "https://www.altitude-sports.com/products/osprey-document-zip-llll-osp-doczip", "tech_specs": {"features": [], "Zip Document Case.": ["40D nylon ripstop", "RFID protection", "Zip closure", "Inner zip pocket options", "Inner card slots"]}, "img_urls": ["https://cdn.shopify.com/s/files/1/1230/9376/products/OSP-DOCZIP_7EPoppy_20Orange_051da58c-75cd-484b-92e9-7dd6df56c79f.jpg?v=1609838037"]}