{"manufacturer": "Oakley", "name": "Fall Line XM - Prizm Rose Lens Replacement", "price": "79.99", "category_hierarchy": ["Gear", "Gear/Ski &amp; Backcountry", "Gear/Ski &amp; Backcountry/Goggles", "Gear/Ski &amp; Backcountry/Replacement Goggle Lenses"], "sku": "oak-103-137-004", "uid": "4428401541223", "review_score": "5", "review_total": "1", "url": "https://www.altitude-sports.com/products/oakley-fall-line-xm-prizm-rose-lens-replacement-llll-oak-103-137-004", "tech_specs": {"features": []}, "img_urls": ["https://cdn.shopify.com/s/files/1/1230/9376/products/OAK-103-137-004_7ENo_20Color.jpg?v=1576218286"]}