{"manufacturer": "Osprey", "name": "Porter 46", "price": "219.99", "category_hierarchy": ["Gear", "Gear/Packs &amp; Bags", "Gear/Packs &amp; Bags/Daypacks &amp; Backpacks"], "sku": "osp-137646", "uid": "8948579974", "review_score": "4.8", "review_total": "5", "url": "https://www.altitude-sports.com/products/osprey-porter-46-llll-osp-137646", "tech_specs": {"features": ["Zippered top pocket provides quick access to toiletries and liquids", "D-ring attachments for adding a shoulder strap (sold separately)", "StraightJacket\u2122 compression with padded wings secures any size load e\u00a4ectively", "Large panel zip access to main compartment with lockable zippers", "Front panel padded organization pocket with lockable zippers, and separate laptop/ tablet sleeves", "Front panel vertical zippered pocket", "Re-enforced cord loops to attach an Osprey Daylite daypack", "Padded top and side handles provide comfortable carry", "Stow-away shoulder harness with adjustable sternum strap and whistle buckle 10 Stow-away padded hipbelt", "Stow-away padded hipbelt Maxiumum legal carry-on size "]}, "img_urls": ["https://cdn.shopify.com/s/files/1/1230/9376/products/OSP-137646_7EHaybale_20Green_845e9158-10f9-4b46-906e-3cbb62e7c496.jpg?v=1616744938"]}