{"manufacturer": "Oakley", "name": "Carbon Blade - Matte Satin Black - Prizm Daily Polarized Lens Sunglasses", "price": "505.99", "category_hierarchy": ["Gear", "Gear/Sunglasses", "Gear/Sunglasses/Casual", "Gear/Sunglasses/Men", "Gear/Sunglasses/Women", "Men", "Women"], "sku": "oak-oo9174-07", "uid": "8828584966", "review_score": "5", "review_total": "1", "url": "https://www.altitude-sports.com/products/oakley-carbon-blade-matte-satin-black-prizm-daily-polarized-lens-sunglasses-llll-oak-oo9174-07", "tech_specs": {"features": []}, "img_urls": ["https://cdn.shopify.com/s/files/1/1230/9376/products/OAK-OO9174-07_7ENo_20Color_8abb570b-3699-4732-8bc2-ac1e236f98fe.jpg?v=1507670478"]}