{"manufacturer": "Patagonia", "name": "Dirt Roamer Jacket - Men's", "price": "285", "category_hierarchy": ["Men", "Men/Jackets &amp; Vests", "Men/Jackets &amp; Vests/Camping &amp; Hiking Coats &amp; Vests"], "sku": "pat-24381", "uid": "4512925188199", "review_score": "4.75", "review_total": "7", "url": "https://www.altitude-sports.com/products/patagonia-dirt-roamer-jacket-mens-llll-pat-24381", "tech_specs": {"features": []}, "img_urls": ["https://cdn.shopify.com/s/files/1/1230/9376/products/PAT-24381_7EWood_20Brown.jpg?v=1616739024"]}