{"manufacturer": "Red Wing Shoes", "name": "Wacouta 6-inch Boots - Men's", "price": "349.99", "category_hierarchy": ["Footwear", "Footwear/Men", "Footwear/Men/Casual Shoes &amp; Urban Boots", "Footwear/Men/Casual Shoes &amp; Urban Boots/Casual Boots", "Footwear/Men/Leather Boots &amp; Shoes", "Men"], "sku": "rwg-3335", "uid": "3853577879655", "review_score": "4", "review_total": "1", "url": "https://www.altitude-sports.com/products/red-wing-shoes-wacouta-6-inch-boots-mens-llll-rwg-3335", "tech_specs": {"features": []}, "img_urls": ["https://cdn.shopify.com/s/files/1/1230/9376/products/RWG-3335_7ECanvas_20-_20Copper.jpg?v=1625293361"]}