{"manufacturer": "Therm-a-Rest", "name": "Sleep Liner", "price": "74.99", "category_hierarchy": ["Gear", "Gear/Sleeping Bags", "Gear/Sleeping Bags/Liners"], "sku": "tar-10282", "uid": "167179878421", "review_score": "4.5", "review_total": "11", "url": "https://www.altitude-sports.com/products/therm-a-rest-sleep-liner-llll-tar-10282", "tech_specs": {"features": ["Brushed Polyester: Soft to the touch and easy to clean between adventures.", "Quilt and Blanket Loops: Customize your sleep system by layering our quilts or tech blankets for increased warmth.", "Added Warmth: Adds up to 5F/3C of warmth to your sleeping bag or quilt for nights when you need extra protection from the cold."]}, "img_urls": ["https://cdn.shopify.com/s/files/1/1230/9376/products/TAR-10282_7EGrey_d24fca20-18d8-400a-a86f-54ba463b10a6.jpg?v=1547531227"]}