{"manufacturer": "UGG", "name": "Hazel Boots - Women's", "price": "189.99", "category_hierarchy": ["Footwear", "Footwear/Women", "Footwear/Women/Casual Shoes &amp; Urban Boots", "Footwear/Women/Leather Boots &amp; Shoes", "Footwear/Women/Waterproof Footwear", "Footwear/Women/Winter Boots", "Women"], "sku": "ugg-1103766", "uid": "4037415075943", "review_score": "4.8824", "review_total": "9", "url": "https://www.altitude-sports.com/products/ugg-hazel-boots-womens-llll-ugg-1103766", "tech_specs": {"features": [], "Waterproof High-Heel Boot.": ["Waterproof suede upper", "Lateral and medial non-wicking gore detail", "Textile/synthetic lining", "Seam-sealed waterproof construction", "Cushioning foam lined w/ synthetic heat embossed detailing", "Moulded rubber outsole\n"]}, "img_urls": ["https://cdn.shopify.com/s/files/1/1230/9376/products/UGG-1103766_7EBlack.jpg?v=1600409446"]}