{"name": "Kombi Candy Man Hat - Children", "categories": ["Home", "All", "Kids", "Toddler and child (2-7 yrs)", "Toddler and child clothing", "Toddler and child accessories", "Toddler and child hats and toques", "Toddler and child winter hats", "Candy Man Hat"], "description": "A classic Peruvian-style toque with pompon and earflaps.Made of acrylic with soft fleeced lining.Earflaps add extra protection to winter\u2019s chill winds.", "product_code": "6002-474", "tech_specs": {"Ideal for": ["Snowsports"], "Fabric content": ["100% acrylic"], "Lining/backer": ["Nylon"], "Windproofness\n\nA windproof garment does not allow any air to permeate the fabric.  A garment with windproof panels has panels of fabric that are totally windproof, but the rest of the garment may not be windproof.  A wind-resistant garment resists some wind, but not as much as a garment that is windproof.": ["Wind-resistant"], "Made in": ["China"]}, "img_urls": ["https://cdn.mec.ca/medias/sys_master/high-res/high-res/9046129279006/6002474-PPF20.jpg", "https://cdn.mec.ca/medias/sys_master/high-res/high-res/9131594350622/6002474-DKN00.jpg", "https://cdn.mec.ca/medias/sys_master/high-res/high-res/9046129279006/6002474-PPF20.jpg", "https://cdn.mec.ca/medias/sys_master/high-res/high-res/9131594350622/6002474-DKN00.jpg"]}