{"name": "NRS 1\" HD Straps (4 Pack)", "categories": ["Home", "All", "Watersports", "Racks, straps, and locks", "Straps and tie downs", "1\" HD Straps (4 Pack)"], "description": "Use these straps to secure your craft to your roof rack.1-inch high-strength webbing, treated to resist UV resistant.2 stainless steel springs per cam buckle improves grip.Tensile strength: 1500lb.Name label.Pack of 4.", "product_code": "6010-837", "tech_specs": {"Ideal for": ["Watersports"], "Made in": ["China"]}, "img_urls": ["https://cdn.mec.ca/medias/sys_master/high-res/high-res/9090029944862/6010837-STH00.jpg"]}