{"name": "Best Day Hikes in Banff National Park", "categories": ["Home", "All", "Travel gear", "Books and maps", "Guidebooks", "Best Day Hikes in Banff National Park"], "description": "Focus your time in Banff on the best hikes the park has to offer. This book outlines the authors' 39 favourite hikes, including detailed descriptions, maps and colour photos as user-friendly as possible.", "product_code": "6011-881", "tech_specs": {"Ideal for": ["Day hiking"], "Regionality": ["Rockies"], "Author": ["Brian Patton, Bart Robinson"], "Language": ["English"], "Pages": ["192"], "Published": ["2019"], "ISBN": ["978-1-926983-39"], "Made in": ["Canada"]}, "img_urls": ["https://cdn.mec.ca/medias/sys_master/high-res/high-res/9153976303646/6011881-NOC02.jpg"]}