{"name": "Marmot Never Summer 0 Sleeping Bag_127862", "categories": [""], "product_code": "127862", "tech_specs": {"Best Use": ["Backpacking", "Backpacking"], "Tested Lower Limit": ["-4.7 degrees (F) - EN", "-4.7 degrees (F) - EN"], "Tested Comfort": ["9.5 degrees (F) - EN", "9.5 degrees (F) - EN"], "Temperature Rating (F)": ["0 degrees (F)", "0 degrees (F)"], "Temperature Rating (C)": ["-17 degrees (C)", "-17 degrees (C)"], "Weight": ["3 lbs. 5 oz.", "3 lbs. 3 oz."], "Shell": ["20-denier mini ripstop nylon", "20-denier mini ripstop nylon"], "Zipper Location": ["Left", "Left"], "Insulation Type": ["Down", "Down"], "Water-Resistant Down": ["Yes", "Yes"], "Fill": ["650-fill-power duck down", "650-fill-power duck down"], "Fill Weight": ["2 lb. 15.7 oz.", "2 lbs. 2.2 oz."], "Lining": ["20-denier nylon plain weave", "20-denier nylon plain weave"], "Sleeping Bag Shape": ["Mummy", "Mummy"], "Fits Up To (in.)": ["78 inches", "72 inches"], "Shoulder Girth (in.)": ["64 inches", "62 inches"], "Hip Girth (in.)": ["59 inches", "57 inches"], "Stuff Sack Size": ["9 x 18 inches", "9 x 18 inches"], "Stuff Sack Volume": ["16.8 liters", "16.8 liters"], "Gender": ["Unisex", "Unisex"], "Sustainability": ["Down certified to the Responsible Down Standard (RDS)", "Down certified to the Responsible Down Standard (RDS)"]}}