{"name": "Selk'Bag Original 6G Wearable Sleeping Bag_171882", "categories": [""], "product_code": "171882", "tech_specs": {"Best Use": ["Camping", "Camping", "Camping", "Camping"], "Temperature Rating (F)": ["40 degrees (F)", "40 degrees (F)", "40 degrees (F)", "40 degrees (F)"], "Temperature Rating (C)": ["4.5 degrees (C)", "4.5 degrees (C)", "4.5 degrees (C)", "4.5 degrees (C)"], "Weight": ["4 lbs. 1.6 oz.", "3 lbs. 12.8 oz.", "3 lbs. 6.4 oz.", "4 lbs. 9.6 oz."], "Shell": ["Ripstop nylon", "Ripstop nylon", "Ripstop nylon", "Ripstop nylon"], "Zipper Location": ["Right", "Right", "Right", "Right"], "Insulation Type": ["Synthetic", "Synthetic", "Synthetic", "Synthetic"], "Fill": ["Synthetic fibers", "Synthetic fibers", "Synthetic fibers", "Synthetic fibers"], "Lining": ["Polyester", "Polyester", "Polyester", "Polyester"], "Sleeping Bag Shape": ["Unavailable", "Unavailable", "Unavailable", "Unavailable"], "Fits Up To (in.)": ["71 inches", "65 inches", "59 inches", "76 inches"], "Shoulder Girth (in.)": ["Unavailable", "Unavailable", "Unavailable", "Unavailable"], "Hip Girth (in.)": ["Unavailable", "Unavailable", "Unavailable", "Unavailable"], "Stuff Sack Size": ["11 x 14.5 inches", "10 x 14.5 inches", "9.5 x 13.7 inches", "11.8 x 14.9 inches"], "Stuff Sack Volume": ["18 liters", "16 liters", "14 liters", "20 liters"], "Gender": ["Unisex", "Unisex", "Unisex", "Unisex"]}}