{"name": "Popular Day Hikes: South-Central Okanagan - R", "categories": ["Home", "All", "Travel gear", "Books and maps", "Guidebooks", "Popular Day Hikes: South-Central Okanagan - R"], "description": "Discover robust vineyards, fruit orchards, desert-like grasslands, rich marshes, ponderosa pine forests, towering cliffs, large lakes, salmon streams, modest peaks and a tremendous diversity of animal and plant life. This guidebook features 35 accessible treks in the Southern Okanagan between the Cascade and Columbia mountain ranges, from Kelowna to Osoyoos. Revised second edition features a fresh design and the most current route updates.", "product_code": "6002-443", "tech_specs": {"Ideal for": ["Day hiking"], "Regionality": ["British Columbia"], "Author": ["Gerry Shea"], "Language": ["English"], "Pages": ["152"], "Published": ["2019"], "Edition": ["2nd"], "ISBN": ["9781771602778"], "Made in": ["Canada"]}, "img_urls": ["https://cdn.mec.ca/medias/sys_master/high-res/high-res/9032070955038/6002443-NOC02.jpg"]}