{"name": "Prana Los Feliz Slim Fit Flannel Long Sleeve Shirt - Men's", "categories": ["Home", "All", "Clothing", "Shirts and tops", "Button up shirts and polos", "Los Feliz Slim Fit Flannel Long Sleeve Shirt"], "description": "Soft flannel for year-round wear. Clean and classic, for city wear or hanging out by the campfire.Single chest patch pocket.Slim fit.\n\n        Sustainability\n\n\n\n\n\n\n.cls-1{fill:none;}.cls-2{fill:none;}\n\nOrganic\n\n\n\n\n\n\n\n\n                      Organically grown content\n\n\n\n\n\n.st0{stroke:#333;stroke-width:.79;stroke-miterlimit:10}\n\n\n\n\n\n\n\n\n                      Recycled content", "product_code": "6010-275", "tech_specs": {"Ideal for": ["Casual wear"], "Fabric content": ["80% organically grown cotton", "20% recycled polyester"], "Pockets": ["1 external chest"], "Product sustainability": ["Organically grown content", "Recycled content"], "Made in": ["India"]}, "img_urls": ["https://cdn.mec.ca/medias/sys_master/high-res/high-res/9140240023582/6010275-CHA00.jpg"]}