{"name": "MSR Snowshoe Strap Keepers", "categories": ["Home", "All", "Ski and snowboard gear", "Snowshoeing gear", "Snowshoe accessories", "Snowshoe Strap Keepers"], "description": "Keep the straps on your MSR snowshoes from getting underfoot. Great as replacement parts or in your field repair kit.Set of 8.", "product_code": "5029-038", "tech_specs": {"Ideal for": ["Snowshoeing"], "Made in": ["Ireland"]}, "img_urls": ["https://cdn.mec.ca/medias/sys_master/high-res/high-res/8817237032990/5029038-NOC02.jpg"]}