{"name": "Kershaw Taskmaster Saw", "categories": ["Home", "All", "Camping and hiking", "Tools and accessories", "Knives and tools", "Saws, axes and camp shovels", "Saws", "Taskmaster Saw"], "description": "Backyard or backcountry, use this compact folding saw for firewood, trail maintenance or   yard work. It cuts easily through branches and small logs.Rugged glass-reinforced nylon handle has rubber panels to add grip.Reliable button-lock is easy to use with or without gloves.High-carbon blade is nickel plated for corrosion resistance.Lanyard hole at the base of the handle.", "product_code": "6011-588", "tech_specs": {"Weight": ["261g"], "Ideal for": ["Backpacking", "Car camping"], "Handle material": ["Glass-reinforced nylon (GRN)", "Rubber"], "Blade material": ["High carbon steel"], "Handle length": ["23.5cm"], "Blade length": ["18.4cm"], "Sheath included": ["No"], "Made in": ["China"]}, "img_urls": ["https://cdn.mec.ca/medias/sys_master/high-res/high-res/9146822885406/6011588-BK031.jpg", "https://cdn.mec.ca/medias/sys_master/high-res/high-res/9146815938590/6011588-BK031-ALT-CLOSED.jpg", "https://cdn.mec.ca/medias/sys_master/high-res/high-res/9146816036894/6011588-BK031-ALT-HALFOPEN.jpg", "https://cdn.mec.ca/medias/sys_master/high-res/high-res/9146822885406/6011588-BK031.jpg", "https://cdn.mec.ca/medias/sys_master/high-res/high-res/9146815938590/6011588-BK031-ALT-CLOSED.jpg", "https://cdn.mec.ca/medias/sys_master/high-res/high-res/9146816036894/6011588-BK031-ALT-HALFOPEN.jpg"]}