{"name": "Outdoor Research Dry Summit Pack HD 28L - Unisex", "categories": ["Home", "All", "Packs and bags", "Daypacks and school bags", "Daypacks", "Dry Summit Pack HD 28L"], "description": "On the approach, this compressible pack easily stuffs in a bigger pack or travel bag. Once you have a camp set up, it works as an ultralight pack for side hikes and summit trips. Big enough for day hikes, it's also waterproof and has a hipbelt for support or to use with the rolltop closure to compress the contents.Made of lightweight nylon ripstop with taped seams and a PU coating for total waterproofness.Padded shoulder straps are covered with air mesh for breathability.Webbing waistbelt can be clipped to the rolltop buckles for additional compression.Water tight roll top closure seals out weather.Waterproof front organizer pocket for small essentials.Ice axe loops, and laser cut lash points offer lots of external gear carry options.Single pull V-shaped compression straps cinch down the load.", "product_code": "6011-426", "tech_specs": {"Weight": ["370g"], "Ideal for": ["Day hiking", "Alpine climbing and mountaineering"], "Main fabric": ["Nylon"], "Access\n\nThe location of all access points into the main compartment of the pack.": ["Top"], "Hipbelt": ["Waistbelt"], "Volume": ["28L"], "Length": ["56cm"], "Width": ["30cm"], "Depth": ["18cm"], "Ventilated back panel": ["No"], "Carry-on sized\n\nSize restrictions vary among airlines. Just to be sure, check with your carrier for their specific restrictions.": ["Yes"], "Additional feature(s)": ["Compression straps", "Ice axe/pole attachment", "Ultralight"], "Made in": ["Vietnam"]}, "img_urls": ["https://cdn.mec.ca/medias/sys_master/high-res/high-res/9128837906462/6011426-BK000.jpg"]}