{"name": "Craft Wild Ride Jersey - Women's", "categories": ["Home", "All", "Cycling", "Cycling clothing", "Cycling tops", "Cycling jerseys", "Short sleeve jerseys", "Wild Ride Jersey"], "description": "Stay comfy as you are ripping through the trees and devouring single-track. Designed in collaboration with Nelson\u2019s Ambler, the Wild Ride gives back to our green spaces and is constructed from 100% recycled polyester.For every jersey purchased, $1 will be donated to CPAWS, Canadian Wilderness and Wildlife Society.Made using recycled polyester that wicks away moisture and dries quickly.Mechanical stretch moves with you.Single zippered pocket on the back side, is just right for a bar and your keys.UPF 25+ UV protection, blocking more than 93% of harmful UV.Loose comfortable fit.\n\n        Sustainability\n\n\n\n\n\n.st0{stroke:#333;stroke-width:.79;stroke-miterlimit:10}\n\n\n\n\n\n\n\n\n                      Recycled content", "product_code": "6015-991", "tech_specs": {"Ideal for": ["Mountain biking"], "Fabric content": ["100% recycled polyester"], "Pockets": ["1 side zippered with cord port"], "UPF rating\n\nThe Ultraviolet Protection Factor rating indicates how effective a fabric is at blocking out solar ultraviolet radiation.": ["15-24 (Blocks ~93% of UVA/UVB)"], "Product sustainability": ["Recycled content"], "Made in": ["China"]}, "img_urls": ["https://cdn.mec.ca/medias/sys_master/high-res/high-res/9187443277854/6015991-TUV00.jpg", "https://cdn.mec.ca/medias/sys_master/high-res/high-res/9187443441694/6015991-TUV00-ALT-BACK.jpg", "https://cdn.mec.ca/medias/sys_master/high-res/high-res/9187443277854/6015991-TUV00.jpg", "https://cdn.mec.ca/medias/sys_master/high-res/high-res/9187443441694/6015991-TUV00-ALT-BACK.jpg"]}